chronos/__init__.py
chronos/cli.py
chronos/conventional_commits.py
chronos/helpers.py
chronos/semver.py
chronos_cli-0.2.12.dist-info/LICENSE
chronos_cli-0.2.12.dist-info/METADATA
chronos_cli-0.2.12.dist-info/WHEEL
chronos_cli-0.2.12.dist-info/entry_points.txt
chronos_cli-0.2.12.dist-info/top_level.txt
chronos_cli-0.2.12.dist-info/RECORD
