Metadata-Version: 2.1
Name: chronos-cli
Version: 0.2.12
Summary: A CLI tool that infers a next version number for Git repos.
Home-page: https://github.com/devoperate/chronos
Author: Claude Léveillé
Author-email: claude-leveille@outlook.com
License: MIT
Platform: UNKNOWN
Classifier: Programming Language :: Python :: 3
Classifier: License :: OSI Approved :: MIT License
Classifier: Operating System :: OS Independent
